CHANGES.txt
LICENSE.txt
MANIFEST.in
README.rst
setup.py
NAMS.egg-info/PKG-INFO
NAMS.egg-info/SOURCES.txt
NAMS.egg-info/dependency_links.txt
NAMS.egg-info/top_level.txt
bin/__init__.py
bin/tester_2mols.py
bin/tester_chirality.py
bin/tester_doubleb_e_z.py
bin/tester_nams.py
nams/__init__.py
nams/chirality.py
nams/doubleb_e_z.py
nams/heuristic.py
nams/nams.py
nams/data/Data_2.smi
nams/data/HC_100.smi
nams/data/nelems_dist0.txt
nams/data/nelems_dist1.txt
nams/data/nelems_dist2.txt
nams/data/nelems_dist3.txt
nams/data/nelems_dist4.txt