Metadata-Version: 1.0
Name: NAMS
Version: 0.9.2
Summary: NAMS is a module to calculate similarity between molecules based on the structural/topological relationships of each atom towards all the others within a molecule.
Home-page: http://nams.lasige.di.fc.ul.pt/
Author: Andre O Falcao and Ana L. Teixeira
Author-email: afalcao@di.fc.ul.pt; ateixeira@lasige.di.fc.ul.pt
License: The NAMS python package calculates the similarity between molecules based on the 
